autohaus/__init__.py
autohaus/_version.py
autohaus-0.0.1.dist-info/METADATA
autohaus-0.0.1.dist-info/WHEEL
autohaus-0.0.1.dist-info/RECORD
